libcatapult/__init__.py
libcatapult/asyncutils/__init__.py
libcatapult/file/__init__.py
libcatapult/geo/__init__.py
libcatapult/geo/s1.py
libcatapult/geo/snap.py
libcatapult/queues/__init__.py
libcatapult/queues/base_queue.py
libcatapult/queues/nats.py
libcatapult/queues/redis.py
libcatapult/storage/__init__.py
libcatapult/storage/s3_tools.py
libcatapult/strings/__init__.py
tests/__init__.py
tests/geo/__init__.py
tests/geo/test_s1.py
tests/queues/__init__.py
tests/queues/test_nats.py
tests/queues/test_redis.py
tests/storage/__init__.py
tests/storage/test_s3_tools.py
libcatapult-0.1.6.dist-info/LICENSE
libcatapult-0.1.6.dist-info/METADATA
libcatapult-0.1.6.dist-info/WHEEL
libcatapult-0.1.6.dist-info/top_level.txt
libcatapult-0.1.6.dist-info/RECORD
