Metadata-Version: 2.1
Name: libcatapult
Version: 0.1.6
Summary: A library of useful code for use in the catapult
Home-page: https://github.com/SatelliteApplicationsCatapult/libcatapult
Author: Emily Selwood
Author-email: emily.selwood@sa.catapult.org.uk
License: apache2
Keywords: catapult library
Platform: UNKNOWN
Classifier: Development Status :: 4 - Beta
Classifier: Intended Audience :: Developers
Classifier: Natural Language :: English
Classifier: Programming Language :: Python :: 3.7
Requires-Dist: asynchronousfilereader (~=0.2.1)
Requires-Dist: boto3 (~=1.12.21)
Requires-Dist: asyncio-nats-client (==0.11.4)
Requires-Dist: redis
